sinupy/EM.py
sinupy/__init__.py
sinupy/draw.py
sinupy/mediums.py
sinupy/algebra/__init__.py
sinupy/algebra/dispersion.py
sinupy/algebra/draw.py
sinupy/algebra/parameter.py
sinupy/algebra/quadratic.py
sinupy/algebra/tensor.py
sinupy/algebra/utility.py
sinupy/mediums/__init__.py
sinupy/mediums/mediums.py
sinupy/mediums/plasma.py
sinupy/waves/EM.py
sinupy/waves/__init__.py
sinupy/waves/waves.py
sinupy-0.1.1.dist-info/LICENSE
sinupy-0.1.1.dist-info/METADATA
sinupy-0.1.1.dist-info/WHEEL
sinupy-0.1.1.dist-info/top_level.txt
sinupy-0.1.1.dist-info/RECORD
